tbm_utils/__about__.py
tbm_utils/__init__.py
tbm_utils/cli.py
tbm_utils/config.py
tbm_utils/constants.py
tbm_utils/datetime.py
tbm_utils/decorators.py
tbm_utils/humanize.py
tbm_utils/io.py
tbm_utils/misc.py
tbm_utils/path.py
tbm_utils/structures.py
tbm_utils-2.5.1.dist-info/LICENSE
tbm_utils-2.5.1.dist-info/WHEEL
tbm_utils-2.5.1.dist-info/METADATA
tbm_utils-2.5.1.dist-info/RECORD
